xtec/GMM.py
xtec/Preprocessing.py
xtec/__init__.py
xtec/_version.py
XTEC-0.1.1.dist-info/LICENSE
XTEC-0.1.1.dist-info/METADATA
XTEC-0.1.1.dist-info/WHEEL
XTEC-0.1.1.dist-info/top_level.txt
XTEC-0.1.1.dist-info/RECORD
